FileSystemModel/__init__.py
FileSystemModel/_dir.py
FileSystemModel/_file.py
FileSystemModel/_path.py
FileSystemModel_Python-0.2.0.dist-info/LICENSE
FileSystemModel_Python-0.2.0.dist-info/METADATA
FileSystemModel_Python-0.2.0.dist-info/WHEEL
FileSystemModel_Python-0.2.0.dist-info/top_level.txt
FileSystemModel_Python-0.2.0.dist-info/RECORD
